{"id":177,"uid":"177-xolmis-pyrope","map":{"svg":"http://www.buscaves.cl/images/svg.php?ave=177"},"image":{"url":"http://www.buscaves.cl/img/13082018080441diucon_barbara_palma_web.jpg","uri":"http://www.buscaves.cl/img/","filename":"13082018080441diucon_barbara_palma_web.jpg","name":"13082018080441diucon_barbara_palma_web","ext":"jpg"},"gallery":[{"url":"http://www.buscaves.cl/img/13082018080441diucon_barbara_palma_web.jpg","uri":"http://www.buscaves.cl/img/","filename":"13082018080441diucon_barbara_palma_web.jpg","name":"13082018080441diucon_barbara_palma_web","ext":"jpg"}],"names":{"spanish":"Diucón","latin":"Xolmis pyrope","english":"Fire-eyed Diucon"},"audio":{"author":"Guillermo Egli","src":"http://www.buscaves.cl/img/09092018082319","type":"audio/wav","ext":"wav","name":"09092018082319","filename":"09092018082319.wav"},"info":{"name":{"name":"Nombre en Inglés","key":"name","value":"Fire-eyed Diucon"},"dimorfism":{"name":"Dimorfismo","key":"dimorfism","value":"No"},"migration":{"name":"Migratoria","key":"migration","value":"Sí"},"size":{"name":"Longitud","key":"size","value":"18 - 22 cm."},"geo":{"name":"Ubicación geográfica","key":"geo","value":"Entre la Región de Coquimbo y la Región de Magallanes"},"order":{"name":"Orden","key":"order","value":"Passeriformes - Suborden Tyranni"},"species":{"name":"Especie","key":"species","value":"Nativa"},"undefined":{"name":"","value":""}},"description":"","habitat":"","iucn":"","didyouknow":""}